easy_sync/__init__.py
easy_sync/py.typed
easy_sync/transform.py
easy_sync-0.2.2.dist-info/LICENSE
easy_sync-0.2.2.dist-info/METADATA
easy_sync-0.2.2.dist-info/WHEEL
easy_sync-0.2.2.dist-info/RECORD
