Metadata-Version: 2.1
Name: easy-sync
Version: 0.2.2
Summary: Provide sync compatibility for your async functions
Home-page: https://github.com/luochen1990/easy-sync
Author: Luo Chen
Author-email: luochen1990@gmail.com
Requires-Python: >=3.10,<4
Classifier: Programming Language :: Python :: 3
Classifier: Programming Language :: Python :: 3.10
Classifier: Programming Language :: Python :: 3.11
Classifier: Programming Language :: Python :: 3.12
Project-URL: Repository, https://github.com/luochen1990/easy-sync
